[
    {
        "id": 0,
        "annonceTitle": "Exemple Annonce 11.03.2021",
        "annonceDescription": "Test",
        "annonceCategorie": "Services",
        "annoncePrice": "201",
        "date": "11.03.2021",
        "user_id": 0,
        "annoncePhoto": "data\\img\\annonces\\1615464624.jpg"
    },
    {
        "id": 1,
        "annonceTitle": "Exemple Annonce 11.03.2021",
        "annonceDescription": "Test",
        "annonceCategorie": "Services",
        "annoncePrice": "201",
        "date": "11.03.2021",
        "user_id": 0,
        "annoncePhoto": "data\\img\\annonces\\1615464629.jpg"
    },
    {
        "id": 2,
        "annonceTitle": "Mercedes amg ",
        "annonceDescription": "La Mercedes-AMG A 45 S ne s'adresse donc clairement pas \u00e0 tout le monde, d'autant qu'il reste encore possible de faire monter la facture en piochant dans la liste des options.",
        "annonceCategorie": "Vente",
        "annoncePrice": "100000",
        "date": "12.03.2021",
        "user_id": 1,
        "annoncePhoto": "data\\img\\annonces\\1615546770.jpg"
    }
]